DeepResidualLearningForImageRecognitionQiyueZaixianDlFanyiZu20174/README.md
DeepResidualLearningForImageRecognitionQiyueZaixianDlFanyiZu20174/__init__.py
DeepResidualLearningForImageRecognitionQiyueZaixianDlFanyiZu20174/__main__.py
DeepResidualLearningForImageRecognitionQiyueZaixianDlFanyiZu20174/file.pdf
DeepResidualLearningForImageRecognitionQiyueZaixianDlFanyiZu20174/index.html
deep_residual_learning_for_image_recognition_qiyue_zaixian_dl_fanyi_zu_2017_4-2024.3.2.0.dist-info/METADATA
deep_residual_learning_for_image_recognition_qiyue_zaixian_dl_fanyi_zu_2017_4-2024.3.2.0.dist-info/WHEEL
deep_residual_learning_for_image_recognition_qiyue_zaixian_dl_fanyi_zu_2017_4-2024.3.2.0.dist-info/entry_points.txt
deep_residual_learning_for_image_recognition_qiyue_zaixian_dl_fanyi_zu_2017_4-2024.3.2.0.dist-info/top_level.txt
deep_residual_learning_for_image_recognition_qiyue_zaixian_dl_fanyi_zu_2017_4-2024.3.2.0.dist-info/RECORD
